utilityhub/__init__.py
utilityhub/sqlite_utils.py
utilityhub-0.1.3.dist-info/LICENSE
utilityhub-0.1.3.dist-info/METADATA
utilityhub-0.1.3.dist-info/WHEEL
utilityhub-0.1.3.dist-info/RECORD
