Metadata-Version: 2.1
Name: UtilityHub
Version: 0.1.3
Summary: Your all-in-one toolkit for everyday development
Author: hyp3r00t
Author-email: rajesh@hyperoot.dev
Requires-Python: >=3.12,<4.0
Classifier: Programming Language :: Python :: 3
Classifier: Programming Language :: Python :: 3.12
Classifier: Programming Language :: Python :: 3.13
